nfv_tempest_plugin/__init__.py
nfv_tempest_plugin/config.py
nfv_tempest_plugin/plugin.py
nfv_tempest_plugin/services/__init__.py
nfv_tempest_plugin/services/heat_client.py
nfv_tempest_plugin/services/keystone_client.py
nfv_tempest_plugin/services/network_client_v2.py
nfv_tempest_plugin/services/nova_client.py
nfv_tempest_plugin/services/os_clients.py
nfv_tempest_plugin/tests/__init__.py
nfv_tempest_plugin/tests/api/__init__.py
nfv_tempest_plugin/tests/common/__init__.py
nfv_tempest_plugin/tests/common/async_utils_manager.py
nfv_tempest_plugin/tests/common/shell_utilities.py
nfv_tempest_plugin/tests/scenario/__init__.py
nfv_tempest_plugin/tests/scenario/baremetal_manager.py
nfv_tempest_plugin/tests/scenario/base_test.py
nfv_tempest_plugin/tests/scenario/manager_utils.py
nfv_tempest_plugin/tests/scenario/qos_manager.py
nfv_tempest_plugin/tests/scenario/test_igmp_snooping_usecases.py
nfv_tempest_plugin/tests/scenario/test_nfv_advanced_usecases.py
nfv_tempest_plugin/tests/scenario/test_nfv_basic.py
nfv_tempest_plugin/tests/scenario/test_nfv_derive_params_usecases.py
nfv_tempest_plugin/tests/scenario/test_nfv_dpdk_usecases.py
nfv_tempest_plugin/tests/scenario/test_nfv_hci_usecases.py
nfv_tempest_plugin/tests/scenario/test_nfv_lacp_usecases.py
nfv_tempest_plugin/tests/scenario/test_nfv_live_migration_usecases.py
nfv_tempest_plugin/tests/scenario/test_nfv_offload.py
nfv_tempest_plugin/tests/scenario/test_nfv_sriov_usecases.py
nfv_tempest_plugin/tests/scenario/day2/__init__.py
nfv_tempest_plugin/tests/scenario/day2/day2_manager.py
nfv_tempest_plugin/tests/scenario/day2/test_hypervisor_usecases.py
nfv_tempest_plugin/tests/scenario/tests_scripts/README.md
nfv_tempest_plugin/tests/scenario/tests_scripts/custom_net_config.py
nfv_tempest_plugin/tests/scenario/tests_scripts/multicast_traffic.py
nfv_tempest_plugin/tests/scenario/tests_scripts/packages_deploy.py
nfv_tempest_plugin/tests/scenario/tests_scripts/post_net_bootstrap.py
tempest_nfv_plugin-1.32.1.dev1.dist-info/AUTHORS
tempest_nfv_plugin-1.32.1.dev1.dist-info/LICENSE
tempest_nfv_plugin-1.32.1.dev1.dist-info/METADATA
tempest_nfv_plugin-1.32.1.dev1.dist-info/WHEEL
tempest_nfv_plugin-1.32.1.dev1.dist-info/entry_points.txt
tempest_nfv_plugin-1.32.1.dev1.dist-info/pbr.json
tempest_nfv_plugin-1.32.1.dev1.dist-info/top_level.txt
tempest_nfv_plugin-1.32.1.dev1.dist-info/RECORD
