Metadata-Version: 2.1
Name: tempest-nfv-plugin
Version: 1.32.1.dev1
Summary: Tempest plugin for testing NFV
Home-page: UNKNOWN
Author: Red Hat NFV QE team
Author-email: nfv-cloud-qe-team@redhat.com
License: Apache Software License
Platform: UNKNOWN
Classifier: Programming Language :: Python
Classifier: Programming Language :: Python :: 3
Classifier: Programming Language :: Python :: 3.6
Classifier: Programming Language :: Python :: 3.7
Classifier: Programming Language :: Python :: 3.8
Classifier: Environment :: OpenStack
Classifier: Intended Audience :: Information Technology
Classifier: Intended Audience :: System Administrators
Classifier: Intended Audience :: Telecommunications Industry
Classifier: Intended Audience :: Other Audience
Classifier: License :: OSI Approved :: Apache Software License
Classifier: Operating System :: POSIX :: Linux
Requires-Dist: tempest (>=16.1.0)
Requires-Dist: configparser (>=3.5.0)
Requires-Dist: envbash (==1.2.0)
Requires-Dist: python-heatclient (==2.3.0)
Requires-Dist: python-keystoneclient (==4.2.0)
Requires-Dist: python-novaclient (==17.4.0)
